<?xml version="1.0" encoding="utf-8" ?><dwsync><file name="issue1_cover.png" server="208.75.252.210" local="3391604940" remote="20571474124" /><file name="issue10_cover.png" server="208.75.252.210" local="3392189700" remote="20572058884" /><file name="issue11_cover.png" server="208.75.252.210" local="3398784600" remote="20578653784" /><file name="issue12_cover.png" server="208.75.252.210" local="3406635720" remote="20586504904" /><file name="issue13_cover.png" server="208.75.252.210" local="3415629120" remote="20595498304" /><file name="issue14_cover.png" server="208.75.252.210" local="3424351200" remote="20604220384" /><file name="issue15_cover.png" server="208.75.252.210" local="3432216000" remote="20612085184" /><file name="issue2_cover.png" server="208.75.252.210" local="3391604940" remote="20571474124" /><file name="issue3_cover.png" server="208.75.252.210" local="3391604940" remote="20571474124" /><file name="issue4_cover.png" server="208.75.252.210" local="3391604940" remote="20571474124" /><file name="issue5_cover.png" server="208.75.252.210" local="3391604940" remote="20571474124" /><file name="issue6_cover.png" server="208.75.252.210" local="3391604940" remote="20571474124" /><file name="issue7_cover.png" server="208.75.252.210" local="3391604940" remote="20571474124" /><file name="issue8_cover.png" server="208.75.252.210" local="3391604940" remote="20571474124" /><file name="issue9_cover.png" server="208.75.252.210" local="3392127060" remote="20571996244" /></dwsync>